Metadata-Version: 2.1
Name: crispml-opus
Version: 0.0.1
Summary: The definitive Python framework for CRISP-ML Methodology Workflows
Home-page: UNKNOWN
Author: R.Costa
Author-email: rafael@aineural.net
License: UNKNOWN
Platform: UNKNOWN
